cloud_curator/__init__.py
cloud_curator/main.py
cloud_curator/aws/__init__.py
cloud_curator/aws/client.py
cloud_curator/reports/__init__.py
cloud_curator/reports/access_keys_rotated.py
cloud_curator_cli-0.1.3.dist-info/LICENSE
cloud_curator_cli-0.1.3.dist-info/METADATA
cloud_curator_cli-0.1.3.dist-info/WHEEL
cloud_curator_cli-0.1.3.dist-info/entry_points.txt
cloud_curator_cli-0.1.3.dist-info/top_level.txt
cloud_curator_cli-0.1.3.dist-info/RECORD
