Metadata-Version: 2.1
Name: cloud-curator-cli
Version: 0.1.3
Summary: UNKNOWN
Home-page: UNKNOWN
Author: Joseph Hissong
Author-email: hissong.joseph@gmail.com
License: MIT License
Requires-Dist: boto3
Requires-Dist: Click
